pydeako/__init__.py
pydeako/py.typed
pydeako/deako/__init__.py
pydeako/deako/_deako.py
pydeako/deako/_manager.py
pydeako/deako/_request.py
pydeako/deako/test_deako.py
pydeako/deako/test_manager.py
pydeako/deako/utils/__init__.py
pydeako/deako/utils/_connection.py
pydeako/deako/utils/_socket.py
pydeako/deako/utils/test_connection.py
pydeako/deako/utils/test_socket.py
pydeako/discover/__init__.py
pydeako/discover/_address_pool.py
pydeako/discover/_discover.py
pydeako/discover/test_address_pool.py
pydeako/discover/test_discover.py
pydeako/models/__init__.py
pydeako/models/_const.py
pydeako/models/_request.py
pydeako/models/test_request.py
pydeako-0.5.3.dist-info/LICENSE.txt
pydeako-0.5.3.dist-info/METADATA
pydeako-0.5.3.dist-info/WHEEL
pydeako-0.5.3.dist-info/top_level.txt
pydeako-0.5.3.dist-info/RECORD
