Metadata-Version: 2.1
Name: pydeako
Version: 0.5.3
Summary: Connect and interact with deako devices over the network locally
Author-email: Deako <software@deako.com>
Project-URL: Homepage, https://github.com/DeakoLights/pydeako
Project-URL: Bug Tracker, https://github.com/DeakoLights/pydeako
Classifier: Development Status :: 3 - Alpha
Classifier: Intended Audience :: Developers
Classifier: Topic :: Home Automation
Classifier: License :: OSI Approved :: MIT License
Classifier: Programming Language :: Python :: 3
Classifier: Programming Language :: Python :: 3.11
Requires-Python: >=3.10
License-File: LICENSE.txt
Requires-Dist: zeroconf
